compendiumscribe-0.3.1.dist-info/METADATA
compendiumscribe-0.3.1.dist-info/WHEEL
compendiumscribe-0.3.1.dist-info/entry_points.txt
compendiumscribe-0.3.1.dist-info/licenses/LICENSE
compendiumscribe/__init__.py
compendiumscribe/cli.py
compendiumscribe/compendium/__init__.py
compendiumscribe/compendium/compendium.py
compendiumscribe/compendium/entities.py
compendiumscribe/compendium/html_site_renderer.py
compendiumscribe/compendium/markdown_renderer.py
compendiumscribe/compendium/payload_parser.py
compendiumscribe/compendium/pdf.py
compendiumscribe/compendium/text_utils.py
compendiumscribe/compendium/xml_parser.py
compendiumscribe/compendium/xml_utils.py
compendiumscribe/create_llm_clients.py
compendiumscribe/prompts/deep_research_assignment.prompt.md
compendiumscribe/prompts/skill_name.prompt.md
compendiumscribe/prompts/skill_writer.prompt.md
compendiumscribe/prompts/topic_blueprint.prompt.md
compendiumscribe/py.typed
compendiumscribe/research/__init__.py
compendiumscribe/research/cancellation.py
compendiumscribe/research/config.py
compendiumscribe/research/errors.py
compendiumscribe/research/execution/__init__.py
compendiumscribe/research/execution/core.py
compendiumscribe/research/execution/polling.py
compendiumscribe/research/orchestrator.py
compendiumscribe/research/parsing.py
compendiumscribe/research/planning.py
compendiumscribe/research/progress.py
compendiumscribe/research/utils.py
compendiumscribe/skill_output.py
compendiumscribe-0.3.1.dist-info/RECORD
