Metadata-Version: 2.1
Name: compendiumscribe
Version: 0.3.1
Summary: A package for automating the creation of comprehensive and organized domain knowledge bases for AI applications.
Author-Email: "B.T. Franklin" <brandon.franklin@gmail.com>
License: MIT License
Classifier: Programming Language :: Python :: 3
Classifier: Programming Language :: Python :: 3 :: Only
Classifier: Programming Language :: Python :: 3.12
Classifier: Programming Language :: Python :: 3.13
Classifier: Programming Language :: Python :: 3.14
Classifier: Typing :: Typed
Classifier: License :: OSI Approved :: MIT License
Classifier: Operating System :: OS Independent
Classifier: Intended Audience :: Developers
Classifier: Topic :: Software Development :: Libraries :: Python Modules
Classifier: Topic :: Software Development :: Code Generators
Classifier: Topic :: Utilities
Classifier: Environment :: Console
Project-URL: Homepage, https://github.com/btfranklin/compendiumscribe
Project-URL: Issues, https://github.com/btfranklin/compendiumscribe/issues
Project-URL: Changelog, https://github.com/btfranklin/compendiumscribe/releases
Project-URL: Repository, https://github.com/btfranklin/compendiumscribe.git
Requires-Python: >=3.12
Requires-Dist: openai>=2.11.0
Requires-Dist: python-dotenv>=1.2.1
Requires-Dist: click>=8.3.1
Requires-Dist: promptdown>=1.1.5
Requires-Dist: mistune>=3.2.0
Requires-Dist: fpdf2>=2.8.5
